hftbacktest-2.4.3.dist-info/METADATA
hftbacktest-2.4.3.dist-info/WHEEL
hftbacktest-2.4.3.dist-info/licenses/LICENSE
hftbacktest.libs/libgcc_s-98a1ef30.so.1
hftbacktest/__init__.py
hftbacktest/_hftbacktest.cpython-311-x86_64-linux-musl.so
hftbacktest/binding.py
hftbacktest/data/__init__.py
hftbacktest/data/utils/__init__.py
hftbacktest/data/utils/binancefutures.py
hftbacktest/data/utils/binancehistmktdata.py
hftbacktest/data/utils/bybithistmktdata.py
hftbacktest/data/utils/databento.py
hftbacktest/data/utils/difforderbooksnapshot.py
hftbacktest/data/utils/feed_order_latency.py
hftbacktest/data/utils/hyperliquid.py
hftbacktest/data/utils/mexc.py
hftbacktest/data/utils/migration2.py
hftbacktest/data/utils/snapshot.py
hftbacktest/data/utils/tardis.py
hftbacktest/data/validation.py
hftbacktest/intrinsic.py
hftbacktest/order.py
hftbacktest/recorder.py
hftbacktest/state.py
hftbacktest/stats/__init__.py
hftbacktest/stats/metrics.py
hftbacktest/stats/stats.py
hftbacktest/stats/utils.py
hftbacktest/types.py
hftbacktest-2.4.3.dist-info/RECORD
